taskrelay.py
test_server.py
taskrelay-0.1.0.dist-info/DESCRIPTION.rst
taskrelay-0.1.0.dist-info/METADATA
taskrelay-0.1.0.dist-info/RECORD
taskrelay-0.1.0.dist-info/WHEEL
taskrelay-0.1.0.dist-info/metadata.json
taskrelay-0.1.0.dist-info/top_level.txt
