Metadata-Version: 2.0
Name: taskrelay
Version: 0.1.0
Summary: A library to run tasks on remote servers
Home-page: https://github.com/muntashir/taskrelay
Author: https://github.com/muntashir
Author-email: UNKNOWN
License: MIT
Platform: UNKNOWN
Requires-Dist: websockets
